[
  {
    "date": "2052-01-01",
    "holiday": "New Year's Day"
  },
  {
    "date": "2052-03-08",
    "holiday": "International Women's Day"
  },
  {
    "date": "2052-03-21",
    "holiday": "Spring Festival"
  },
  {
    "date": "2052-03-22",
    "holiday": "Spring Festival"
  },
  {
    "date": "2052-05-18",
    "holiday": "Constitution and State Flag Day"
  },
  {
    "date": "2052-05-29",
    "holiday": "Eid al-Fitr (estimated)"
  },
  {
    "date": "2052-08-05",
    "holiday": "Eid al-Adha (estimated)"
  },
  {
    "date": "2052-09-27",
    "holiday": "Independence Day"
  },
  {
    "date": "2052-10-06",
    "holiday": "Memorial Day"
  },
  {
    "date": "2052-10-07",
    "holiday": "Memorial Day (observed)"
  },
  {
    "date": "2052-12-12",
    "holiday": "International Neutrality Day"
  }
]