[
  {
    "date": "2019-01-01",
    "holiday": "New Year's Day"
  },
  {
    "date": "2019-03-03",
    "holiday": "Veteran's Day"
  },
  {
    "date": "2019-04-19",
    "holiday": "Holy Friday"
  },
  {
    "date": "2019-05-01",
    "holiday": "International Worker's Day"
  },
  {
    "date": "2019-05-20",
    "holiday": "Restoration of Independence Day"
  },
  {
    "date": "2019-06-06",
    "holiday": "Eid al-Fitr"
  },
  {
    "date": "2019-06-20",
    "holiday": "Corpus Christi"
  },
  {
    "date": "2019-08-11",
    "holiday": "Eid al-Adha"
  },
  {
    "date": "2019-08-30",
    "holiday": "Popular Consultation Day"
  },
  {
    "date": "2019-11-01",
    "holiday": "All Saints' Day"
  },
  {
    "date": "2019-11-02",
    "holiday": "All Souls' Day"
  },
  {
    "date": "2019-11-12",
    "holiday": "National Youth Day"
  },
  {
    "date": "2019-11-28",
    "holiday": "Proclamation of Independence Day"
  },
  {
    "date": "2019-12-07",
    "holiday": "Memorial Day"
  },
  {
    "date": "2019-12-08",
    "holiday": "Day of Our Lady of Immaculate Conception and Timor-Leste Patroness"
  },
  {
    "date": "2019-12-25",
    "holiday": "Christmas Day"
  },
  {
    "date": "2019-12-31",
    "holiday": "National Heroes Day"
  }
]