[
  {
    "date": "2047-01-01",
    "holiday": "New Year's Day"
  },
  {
    "date": "2047-01-08",
    "holiday": "Prophet Mohammed's Birthday (estimated)"
  },
  {
    "date": "2047-04-12",
    "holiday": "Good Friday"
  },
  {
    "date": "2047-04-13",
    "holiday": "Easter Saturday"
  },
  {
    "date": "2047-04-15",
    "holiday": "Easter Monday"
  },
  {
    "date": "2047-05-13",
    "holiday": "Girmit Day"
  },
  {
    "date": "2047-05-31",
    "holiday": "Ratu Sir Lala Sukuna Day"
  },
  {
    "date": "2047-10-10",
    "holiday": "Fiji Day"
  },
  {
    "date": "2047-12-25",
    "holiday": "Christmas Day"
  },
  {
    "date": "2047-12-26",
    "holiday": "Boxing Day"
  },
  {
    "date": "2047-12-29",
    "holiday": "Prophet Mohammed's Birthday (estimated)"
  },
  {
    "date": "2047-12-30",
    "holiday": "Prophet Mohammed's Birthday (observed, estimated)"
  }
]