[
  {
    "date": "2026-01-01",
    "holiday": "New Year's Day"
  },
  {
    "date": "2026-03-20",
    "holiday": "Eid al-Fitr (estimated)"
  },
  {
    "date": "2026-04-06",
    "holiday": "Easter Monday"
  },
  {
    "date": "2026-04-17",
    "holiday": "Women's Rights Day"
  },
  {
    "date": "2026-05-01",
    "holiday": "Labour Day"
  },
  {
    "date": "2026-05-14",
    "holiday": "Ascension Day"
  },
  {
    "date": "2026-05-25",
    "holiday": "Whit Monday"
  },
  {
    "date": "2026-05-27",
    "holiday": "Eid al-Adha (estimated)"
  },
  {
    "date": "2026-08-15",
    "holiday": "Assumption Day"
  },
  {
    "date": "2026-08-16",
    "holiday": "Independence Day"
  },
  {
    "date": "2026-08-17",
    "holiday": "Independence Day Holiday"
  },
  {
    "date": "2026-11-01",
    "holiday": "All Saints' Day"
  },
  {
    "date": "2026-12-25",
    "holiday": "Christmas Day"
  }
]