[
  {
    "date": "2022-01-01",
    "holiday": "New Year's Day"
  },
  {
    "date": "2022-02-01",
    "holiday": "Lunar New Year"
  },
  {
    "date": "2022-02-23",
    "holiday": "National Day"
  },
  {
    "date": "2022-02-28",
    "holiday": "Isra' and Mi'raj"
  },
  {
    "date": "2022-04-03",
    "holiday": "First Day of Ramadan"
  },
  {
    "date": "2022-04-04",
    "holiday": "First Day of Ramadan (observed)"
  },
  {
    "date": "2022-04-19",
    "holiday": "Anniversary of the revelation of the Quran"
  },
  {
    "date": "2022-05-02",
    "holiday": "Eid al-Fitr"
  },
  {
    "date": "2022-05-03",
    "holiday": "Eid al-Fitr"
  },
  {
    "date": "2022-05-04",
    "holiday": "Eid al-Fitr"
  },
  {
    "date": "2022-05-31",
    "holiday": "Armed Forces Day"
  },
  {
    "date": "2022-07-09",
    "holiday": "Eid al-Adha"
  },
  {
    "date": "2022-07-15",
    "holiday": "Sultan Hassanal Bolkiah's Birthday"
  },
  {
    "date": "2022-07-16",
    "holiday": "Sultan Hassanal Bolkiah's Birthday (observed)"
  },
  {
    "date": "2022-07-30",
    "holiday": "Islamic New Year"
  },
  {
    "date": "2022-10-08",
    "holiday": "Prophet's Birthday"
  },
  {
    "date": "2022-12-25",
    "holiday": "Christmas Day"
  },
  {
    "date": "2022-12-26",
    "holiday": "Christmas Day (observed)"
  }
]