[
  {
    "date": "2057-01-01",
    "holiday": "New Year's Day"
  },
  {
    "date": "2057-02-23",
    "holiday": "Republic Day"
  },
  {
    "date": "2057-04-20",
    "holiday": "Good Friday"
  },
  {
    "date": "2057-04-23",
    "holiday": "Easter Monday"
  },
  {
    "date": "2057-05-01",
    "holiday": "Labor Day"
  },
  {
    "date": "2057-05-05",
    "holiday": "Arrival Day"
  },
  {
    "date": "2057-05-26",
    "holiday": "Independence Day"
  },
  {
    "date": "2057-06-13",
    "holiday": "Eid al-Adha (estimated)"
  },
  {
    "date": "2057-07-02",
    "holiday": "CARICOM Day"
  },
  {
    "date": "2057-08-01",
    "holiday": "Emancipation Day"
  },
  {
    "date": "2057-09-12",
    "holiday": "Prophet's Birthday (estimated)"
  },
  {
    "date": "2057-12-25",
    "holiday": "Christmas Day"
  },
  {
    "date": "2057-12-26",
    "holiday": "Day after Christmas"
  }
]