[
  {
    "date": "2041-01-01",
    "holiday": "New Year's Day"
  },
  {
    "date": "2041-02-05",
    "holiday": "Unity Day"
  },
  {
    "date": "2041-04-06",
    "holiday": "Commemoration of the Assassination of President Cyprien Ntaryamira"
  },
  {
    "date": "2041-05-01",
    "holiday": "International Labor Day"
  },
  {
    "date": "2041-05-30",
    "holiday": "Ascension Day"
  },
  {
    "date": "2041-06-08",
    "holiday": "National Day of Patriotism and Commemoration of the Death of President Pierre Nkurunziza"
  },
  {
    "date": "2041-07-01",
    "holiday": "Independence Day"
  },
  {
    "date": "2041-08-15",
    "holiday": "Assumption Day"
  },
  {
    "date": "2041-09-26",
    "holiday": "Eid al-Fitr (estimated)"
  },
  {
    "date": "2041-10-13",
    "holiday": "Commemoration of the Assassination of National Hero, Prince Louis Rwagasore"
  },
  {
    "date": "2041-10-14",
    "holiday": "Commemoration of the Assassination of National Hero, Prince Louis Rwagasore (observed)"
  },
  {
    "date": "2041-10-21",
    "holiday": "Commemoration of the Assassination of President Melchior Ndadaye"
  },
  {
    "date": "2041-11-01",
    "holiday": "All Saints' Day"
  },
  {
    "date": "2041-12-04",
    "holiday": "Eid al-Adha (estimated)"
  },
  {
    "date": "2041-12-25",
    "holiday": "Christmas Day"
  }
]