[
  {
    "date": "2036-01-01",
    "holiday": "New Year's Day"
  },
  {
    "date": "2036-04-11",
    "holiday": "Good Friday"
  },
  {
    "date": "2036-06-14",
    "holiday": "Liberation Day"
  },
  {
    "date": "2036-06-16",
    "holiday": "Liberation Day (observed)"
  },
  {
    "date": "2036-10-06",
    "holiday": "Peat Cutting Day"
  },
  {
    "date": "2036-11-14",
    "holiday": "King's Birthday"
  },
  {
    "date": "2036-12-25",
    "holiday": "Christmas Day"
  },
  {
    "date": "2036-12-26",
    "holiday": "Boxing Day"
  },
  {
    "date": "2036-12-27",
    "holiday": "Christmas Holiday"
  },
  {
    "date": "2036-12-29",
    "holiday": "Christmas Holiday (observed)"
  }
]