[
  {
    "date": "2043-01-01",
    "holiday": "New Year's Day"
  },
  {
    "date": "2043-03-08",
    "holiday": "International Women's Day"
  },
  {
    "date": "2043-03-09",
    "holiday": "International Women's Day (observed)"
  },
  {
    "date": "2043-03-12",
    "holiday": "Youth Day"
  },
  {
    "date": "2043-03-27",
    "holiday": "Good Friday"
  },
  {
    "date": "2043-03-28",
    "holiday": "Holy Saturday"
  },
  {
    "date": "2043-03-30",
    "holiday": "Easter Monday"
  },
  {
    "date": "2043-04-28",
    "holiday": "Kenneth Kaunda Day"
  },
  {
    "date": "2043-05-01",
    "holiday": "Labour Day"
  },
  {
    "date": "2043-05-25",
    "holiday": "Africa Freedom Day"
  },
  {
    "date": "2043-07-06",
    "holiday": "Heroes' Day"
  },
  {
    "date": "2043-07-07",
    "holiday": "Unity Day"
  },
  {
    "date": "2043-08-03",
    "holiday": "Farmers' Day"
  },
  {
    "date": "2043-10-18",
    "holiday": "National Prayer Day"
  },
  {
    "date": "2043-10-19",
    "holiday": "National Prayer Day (observed)"
  },
  {
    "date": "2043-10-24",
    "holiday": "Independence Day"
  },
  {
    "date": "2043-12-25",
    "holiday": "Christmas Day"
  }
]