[
  {
    "date": "2026-01-01",
    "holiday": "New Year's Day"
  },
  {
    "date": "2026-01-02",
    "holiday": "New Year's Day"
  },
  {
    "date": "2026-02-08",
    "holiday": "Prešeren's Day, the Slovenian Cultural Holiday"
  },
  {
    "date": "2026-04-05",
    "holiday": "Easter Sunday"
  },
  {
    "date": "2026-04-06",
    "holiday": "Easter Monday"
  },
  {
    "date": "2026-04-27",
    "holiday": "Day of Uprising Against Occupation"
  },
  {
    "date": "2026-05-01",
    "holiday": "Labor Day"
  },
  {
    "date": "2026-05-02",
    "holiday": "Labor Day"
  },
  {
    "date": "2026-05-24",
    "holiday": "Whit Sunday"
  },
  {
    "date": "2026-06-25",
    "holiday": "Statehood Day"
  },
  {
    "date": "2026-08-15",
    "holiday": "Assumption Day"
  },
  {
    "date": "2026-10-31",
    "holiday": "Reformation Day"
  },
  {
    "date": "2026-11-01",
    "holiday": "Day of Remembrance for the Dead"
  },
  {
    "date": "2026-12-25",
    "holiday": "Christmas Day"
  },
  {
    "date": "2026-12-26",
    "holiday": "Independence and Unity Day"
  }
]