[
  {
    "date": "2042-01-01",
    "holiday": "New Year's Day"
  },
  {
    "date": "2042-01-02",
    "holiday": "Ashura (estimated)"
  },
  {
    "date": "2042-02-18",
    "holiday": "Independence Day"
  },
  {
    "date": "2042-03-04",
    "holiday": "Prophet's Birthday (estimated)"
  },
  {
    "date": "2042-04-04",
    "holiday": "Good Friday"
  },
  {
    "date": "2042-04-07",
    "holiday": "Easter Monday"
  },
  {
    "date": "2042-05-01",
    "holiday": "Labor Day"
  },
  {
    "date": "2042-05-25",
    "holiday": "Africa Liberation Day"
  },
  {
    "date": "2042-05-26",
    "holiday": "Africa Liberation Day (observed)"
  },
  {
    "date": "2042-07-22",
    "holiday": "July 22 Revolution Day"
  },
  {
    "date": "2042-08-15",
    "holiday": "Assumption Day"
  },
  {
    "date": "2042-09-12",
    "holiday": "Laylat al-Qadr (estimated)"
  },
  {
    "date": "2042-09-15",
    "holiday": "Eid al-Fitr (estimated)"
  },
  {
    "date": "2042-09-16",
    "holiday": "Eid al-Fitr (estimated)"
  },
  {
    "date": "2042-11-23",
    "holiday": "Eid al-Adha (estimated)"
  },
  {
    "date": "2042-11-24",
    "holiday": "Eid al-Adha (estimated)"
  },
  {
    "date": "2042-12-23",
    "holiday": "Ashura (estimated)"
  },
  {
    "date": "2042-12-25",
    "holiday": "Christmas Day"
  },
  {
    "date": "2042-12-26",
    "holiday": "Boxing Day"
  }
]