[
  {
    "date": "2048-01-01",
    "holiday": "New Year's Day"
  },
  {
    "date": "2048-01-04",
    "holiday": "Independence Day"
  },
  {
    "date": "2048-02-12",
    "holiday": "Union Day"
  },
  {
    "date": "2048-02-14",
    "holiday": "Chinese New Year"
  },
  {
    "date": "2048-02-27",
    "holiday": "Full Moon Day of Tabaung"
  },
  {
    "date": "2048-03-02",
    "holiday": "Peasants' Day"
  },
  {
    "date": "2048-03-27",
    "holiday": "Armed Forces Day"
  },
  {
    "date": "2048-04-13",
    "holiday": "Myanmar New Year"
  },
  {
    "date": "2048-04-14",
    "holiday": "Myanmar New Year"
  },
  {
    "date": "2048-04-15",
    "holiday": "Myanmar New Year"
  },
  {
    "date": "2048-04-16",
    "holiday": "Myanmar New Year"
  },
  {
    "date": "2048-04-17",
    "holiday": "Myanmar New Year"
  },
  {
    "date": "2048-04-18",
    "holiday": "Myanmar New Year"
  },
  {
    "date": "2048-04-19",
    "holiday": "Myanmar New Year"
  },
  {
    "date": "2048-04-20",
    "holiday": "Myanmar New Year"
  },
  {
    "date": "2048-04-21",
    "holiday": "Myanmar New Year"
  },
  {
    "date": "2048-04-26",
    "holiday": "Full Moon Day of Kason"
  },
  {
    "date": "2048-05-01",
    "holiday": "May Day"
  },
  {
    "date": "2048-07-19",
    "holiday": "Martyrs' Day"
  },
  {
    "date": "2048-07-25",
    "holiday": "Full Moon Day of Waso"
  },
  {
    "date": "2048-09-20",
    "holiday": "Eid al-Adha (estimated)"
  },
  {
    "date": "2048-10-21",
    "holiday": "Thadingyut Holidays"
  },
  {
    "date": "2048-10-22",
    "holiday": "Thadingyut Holidays"
  },
  {
    "date": "2048-10-23",
    "holiday": "Thadingyut Holidays"
  },
  {
    "date": "2048-11-06",
    "holiday": "Diwali"
  },
  {
    "date": "2048-11-20",
    "holiday": "Full Moon Day of Tazaungmon"
  },
  {
    "date": "2048-11-30",
    "holiday": "National Day"
  },
  {
    "date": "2048-12-25",
    "holiday": "Christmas Day"
  }
]