[
  {
    "date": "2049-02-15",
    "holiday": "Liberation Day"
  },
  {
    "date": "2049-04-28",
    "holiday": "Mojahedin's Victory Day"
  },
  {
    "date": "2049-06-02",
    "holiday": "First Day of Ramadan (estimated)"
  },
  {
    "date": "2049-07-01",
    "holiday": "Eid al-Fitr (estimated)"
  },
  {
    "date": "2049-07-02",
    "holiday": "Eid al-Fitr (estimated)"
  },
  {
    "date": "2049-07-03",
    "holiday": "Eid al-Fitr (estimated)"
  },
  {
    "date": "2049-08-14",
    "holiday": "Islamic Emirate Victory Day"
  },
  {
    "date": "2049-08-19",
    "holiday": "Afghanistan Independence Day"
  },
  {
    "date": "2049-08-31",
    "holiday": "American Withdrawal Day"
  },
  {
    "date": "2049-09-07",
    "holiday": "Day of Arafah (estimated)"
  },
  {
    "date": "2049-09-08",
    "holiday": "Eid al-Adha (estimated)"
  },
  {
    "date": "2049-09-09",
    "holiday": "Eid al-Adha (estimated)"
  },
  {
    "date": "2049-09-10",
    "holiday": "Eid al-Adha (estimated)"
  },
  {
    "date": "2049-12-07",
    "holiday": "Prophet's Birthday (estimated)"
  }
]