[
  {
    "date": "2027-01-01",
    "holiday": "Founding Day of the Republic of China"
  },
  {
    "date": "2027-02-04",
    "holiday": "Chinese New Year's Eve"
  },
  {
    "date": "2027-02-05",
    "holiday": "Chinese New Year's Eve"
  },
  {
    "date": "2027-02-06",
    "holiday": "Chinese New Year"
  },
  {
    "date": "2027-02-07",
    "holiday": "Chinese New Year"
  },
  {
    "date": "2027-02-08",
    "holiday": "Chinese New Year"
  },
  {
    "date": "2027-02-09",
    "holiday": "Chinese New Year (observed)"
  },
  {
    "date": "2027-02-10",
    "holiday": "Chinese New Year (observed)"
  },
  {
    "date": "2027-02-28",
    "holiday": "Peace Memorial Day"
  },
  {
    "date": "2027-03-01",
    "holiday": "Peace Memorial Day (observed)"
  },
  {
    "date": "2027-04-04",
    "holiday": "Children's Day"
  },
  {
    "date": "2027-04-05",
    "holiday": "Tomb-Sweeping Day"
  },
  {
    "date": "2027-04-06",
    "holiday": "Children's Day (observed)"
  },
  {
    "date": "2027-05-01",
    "holiday": "Labor Day"
  },
  {
    "date": "2027-06-09",
    "holiday": "Dragon Boat Festival"
  },
  {
    "date": "2027-09-15",
    "holiday": "Mid-Autumn Festival"
  },
  {
    "date": "2027-09-28",
    "holiday": "Confucius' Birthday"
  },
  {
    "date": "2027-10-10",
    "holiday": "National Day"
  },
  {
    "date": "2027-10-11",
    "holiday": "National Day (observed)"
  },
  {
    "date": "2027-10-25",
    "holiday": "Taiwan Restoration and Guningtou Victory Memorial Day"
  },
  {
    "date": "2027-12-25",
    "holiday": "Constitution Day"
  },
  {
    "date": "2027-12-31",
    "holiday": "Founding Day of the Republic of China (observed)"
  }
]