[
  {
    "date": "2042-02-17",
    "holiday": "Anniversary of the February 17 Revolution"
  },
  {
    "date": "2042-03-04",
    "holiday": "Prophet's Birthday (estimated)"
  },
  {
    "date": "2042-05-01",
    "holiday": "Labor Day"
  },
  {
    "date": "2042-08-14",
    "holiday": "National Environmental Sanitation Day"
  },
  {
    "date": "2042-09-15",
    "holiday": "Eid al-Fitr (estimated)"
  },
  {
    "date": "2042-09-16",
    "holiday": "Eid al-Fitr (estimated); Martyrs' Day"
  },
  {
    "date": "2042-09-17",
    "holiday": "Eid al-Fitr (estimated)"
  },
  {
    "date": "2042-10-23",
    "holiday": "Liberation Day"
  },
  {
    "date": "2042-11-22",
    "holiday": "Day of Arafah (estimated)"
  },
  {
    "date": "2042-11-23",
    "holiday": "Eid al-Adha (estimated)"
  },
  {
    "date": "2042-11-24",
    "holiday": "Eid al-Adha (estimated)"
  },
  {
    "date": "2042-11-25",
    "holiday": "Eid al-Adha (estimated)"
  },
  {
    "date": "2042-12-14",
    "holiday": "Islamic New Year (estimated)"
  },
  {
    "date": "2042-12-24",
    "holiday": "Independence Day"
  }
]