[
  {
    "date": "2035-01-01",
    "holiday": "New Year's Day"
  },
  {
    "date": "2035-02-17",
    "holiday": "Arafat Day (estimated)"
  },
  {
    "date": "2035-02-18",
    "holiday": "Eid al-Adha (estimated)"
  },
  {
    "date": "2035-02-19",
    "holiday": "Eid al-Adha Holiday (estimated)"
  },
  {
    "date": "2035-02-20",
    "holiday": "Eid al-Adha Holiday (estimated)"
  },
  {
    "date": "2035-03-11",
    "holiday": "Islamic New Year (estimated)"
  },
  {
    "date": "2035-05-01",
    "holiday": "Labor Day"
  },
  {
    "date": "2035-05-20",
    "holiday": "Prophet's Birthday (estimated)"
  },
  {
    "date": "2035-05-25",
    "holiday": "Independence Day"
  },
  {
    "date": "2035-09-29",
    "holiday": "Isra' and Mi'raj (estimated)"
  },
  {
    "date": "2035-12-01",
    "holiday": "Eid al-Fitr (estimated)"
  },
  {
    "date": "2035-12-02",
    "holiday": "Eid al-Fitr Holiday (estimated)"
  },
  {
    "date": "2035-12-03",
    "holiday": "Eid al-Fitr Holiday (estimated)"
  },
  {
    "date": "2035-12-25",
    "holiday": "Christmas Day"
  }
]