[
  {
    "date": "2042-01-01",
    "holiday": "New Year's Day"
  },
  {
    "date": "2042-03-08",
    "holiday": "Women's Day"
  },
  {
    "date": "2042-03-29",
    "holiday": "Martyrs' Day"
  },
  {
    "date": "2042-04-06",
    "holiday": "Easter Sunday"
  },
  {
    "date": "2042-04-07",
    "holiday": "Easter Monday"
  },
  {
    "date": "2042-05-01",
    "holiday": "Labor Day"
  },
  {
    "date": "2042-05-15",
    "holiday": "Ascension Day"
  },
  {
    "date": "2042-05-25",
    "holiday": "Whit Sunday"
  },
  {
    "date": "2042-05-26",
    "holiday": "Whit Monday"
  },
  {
    "date": "2042-06-01",
    "holiday": "Mother's Day"
  },
  {
    "date": "2042-06-15",
    "holiday": "Father's Day"
  },
  {
    "date": "2042-06-26",
    "holiday": "Independence Day"
  },
  {
    "date": "2042-08-15",
    "holiday": "Assumption Day"
  },
  {
    "date": "2042-11-01",
    "holiday": "All Saints' Day"
  },
  {
    "date": "2042-12-11",
    "holiday": "Republic Day"
  },
  {
    "date": "2042-12-25",
    "holiday": "Christmas Day"
  }
]