[
  {
    "date": "2049-01-01",
    "holiday": "New Year's Day"
  },
  {
    "date": "2049-01-15",
    "holiday": "George Price Day"
  },
  {
    "date": "2049-03-08",
    "holiday": "National Heroes and Benefactors Day (observed)"
  },
  {
    "date": "2049-04-16",
    "holiday": "Good Friday"
  },
  {
    "date": "2049-04-17",
    "holiday": "Holy Saturday"
  },
  {
    "date": "2049-04-19",
    "holiday": "Easter Monday"
  },
  {
    "date": "2049-05-01",
    "holiday": "Labour Day"
  },
  {
    "date": "2049-08-02",
    "holiday": "Emancipation Day (observed)"
  },
  {
    "date": "2049-09-10",
    "holiday": "Saint George's Caye Day"
  },
  {
    "date": "2049-09-21",
    "holiday": "Independence Day"
  },
  {
    "date": "2049-10-11",
    "holiday": "Indigenous Peoples' Resistance Day (observed)"
  },
  {
    "date": "2049-11-19",
    "holiday": "Garifuna Settlement Day"
  },
  {
    "date": "2049-12-25",
    "holiday": "Christmas Day"
  },
  {
    "date": "2049-12-27",
    "holiday": "Boxing Day (observed)"
  }
]