[
  {
    "date": "2021-01-01",
    "holiday": "New Year's Day"
  },
  {
    "date": "2021-01-09",
    "holiday": "Martyrs' Day"
  },
  {
    "date": "2021-02-16",
    "holiday": "Carnival Tuesday"
  },
  {
    "date": "2021-04-02",
    "holiday": "Good Friday"
  },
  {
    "date": "2021-05-01",
    "holiday": "Labor Day"
  },
  {
    "date": "2021-11-03",
    "holiday": "Separation Day"
  },
  {
    "date": "2021-11-05",
    "holiday": "Colon Day"
  },
  {
    "date": "2021-11-10",
    "holiday": "Los Santos Uprising Day"
  },
  {
    "date": "2021-11-28",
    "holiday": "Independence Day"
  },
  {
    "date": "2021-11-29",
    "holiday": "Independence Day (observed)"
  },
  {
    "date": "2021-12-08",
    "holiday": "Mother's Day"
  },
  {
    "date": "2021-12-25",
    "holiday": "Christmas Day"
  }
]