[
  {
    "date": "2024-01-01",
    "holiday": "New Year's Day"
  },
  {
    "date": "2024-02-24",
    "holiday": "Independence Day"
  },
  {
    "date": "2024-03-29",
    "holiday": "Good Friday"
  },
  {
    "date": "2024-03-31",
    "holiday": "Easter Sunday"
  },
  {
    "date": "2024-05-01",
    "holiday": "Spring Day"
  },
  {
    "date": "2024-05-19",
    "holiday": "Whit Sunday"
  },
  {
    "date": "2024-06-23",
    "holiday": "Victory Day"
  },
  {
    "date": "2024-06-24",
    "holiday": "Midsummer Day"
  },
  {
    "date": "2024-08-20",
    "holiday": "Independence Restoration Day"
  },
  {
    "date": "2024-12-24",
    "holiday": "Christmas Eve"
  },
  {
    "date": "2024-12-25",
    "holiday": "Christmas Day"
  },
  {
    "date": "2024-12-26",
    "holiday": "Second Day of Christmas"
  }
]