[
  {
    "date": "2029-01-01",
    "holiday": "New Year's Day"
  },
  {
    "date": "2029-03-03",
    "holiday": "Liberation Day"
  },
  {
    "date": "2029-03-05",
    "holiday": "Liberation Day (observed)"
  },
  {
    "date": "2029-04-06",
    "holiday": "Good Friday"
  },
  {
    "date": "2029-04-07",
    "holiday": "Holy Saturday"
  },
  {
    "date": "2029-04-08",
    "holiday": "Easter"
  },
  {
    "date": "2029-04-09",
    "holiday": "Easter"
  },
  {
    "date": "2029-05-01",
    "holiday": "Labor Day and International Workers' Solidarity Day"
  },
  {
    "date": "2029-05-06",
    "holiday": "Saint George's Day (Day of the Bulgarian Army)"
  },
  {
    "date": "2029-05-07",
    "holiday": "Saint George's Day (Day of the Bulgarian Army) (observed)"
  },
  {
    "date": "2029-05-24",
    "holiday": "Day of Slavonic Alphabet, Bulgarian Enlightenment and Culture"
  },
  {
    "date": "2029-09-06",
    "holiday": "Unification Day"
  },
  {
    "date": "2029-09-22",
    "holiday": "Independence Day"
  },
  {
    "date": "2029-09-24",
    "holiday": "Independence Day (observed)"
  },
  {
    "date": "2029-12-24",
    "holiday": "Christmas Eve"
  },
  {
    "date": "2029-12-25",
    "holiday": "Christmas Day"
  },
  {
    "date": "2029-12-26",
    "holiday": "Christmas Day"
  }
]