[
  {
    "date": "2027-01-01",
    "holiday": "New Year's Day"
  },
  {
    "date": "2027-03-09",
    "holiday": "Eid-al-Fitr (estimated)"
  },
  {
    "date": "2027-03-26",
    "holiday": "Good Friday"
  },
  {
    "date": "2027-03-29",
    "holiday": "Easter Monday"
  },
  {
    "date": "2027-05-01",
    "holiday": "Labor Day"
  },
  {
    "date": "2027-06-01",
    "holiday": "Madaraka Day"
  },
  {
    "date": "2027-10-10",
    "holiday": "Mazingira Day"
  },
  {
    "date": "2027-10-11",
    "holiday": "Mazingira Day (observed)"
  },
  {
    "date": "2027-10-20",
    "holiday": "Mashujaa Day"
  },
  {
    "date": "2027-12-12",
    "holiday": "Jamhuri Day"
  },
  {
    "date": "2027-12-13",
    "holiday": "Jamhuri Day (observed)"
  },
  {
    "date": "2027-12-25",
    "holiday": "Christmas Day"
  },
  {
    "date": "2027-12-26",
    "holiday": "Boxing Day"
  },
  {
    "date": "2027-12-27",
    "holiday": "Boxing Day (observed)"
  }
]