[
  {
    "date": "2043-01-01",
    "holiday": "New Year's Day"
  },
  {
    "date": "2043-02-22",
    "holiday": "Mawlid al-Nabi (estimated)"
  },
  {
    "date": "2043-05-01",
    "holiday": "Labor Day"
  },
  {
    "date": "2043-05-25",
    "holiday": "Africa Day"
  },
  {
    "date": "2043-09-04",
    "holiday": "Eid al-Fitr (estimated)"
  },
  {
    "date": "2043-09-05",
    "holiday": "Eid al-Fitr (estimated)"
  },
  {
    "date": "2043-11-12",
    "holiday": "Eid al-Adha (estimated)"
  },
  {
    "date": "2043-11-13",
    "holiday": "Eid al-Adha (estimated)"
  },
  {
    "date": "2043-11-28",
    "holiday": "Independence Day"
  },
  {
    "date": "2043-12-03",
    "holiday": "Islamic New Year (estimated)"
  }
]